ProgramizSwiftJiaochengChuyi/README.md
ProgramizSwiftJiaochengChuyi/__init__.py
ProgramizSwiftJiaochengChuyi/__main__.py
ProgramizSwiftJiaochengChuyi/file.epub
ProgramizSwiftJiaochengChuyi/index.html
ProgramizSwiftJiaochengChuyi/css/__init__.py
ProgramizSwiftJiaochengChuyi/css/annotations.css
ProgramizSwiftJiaochengChuyi/css/main.css
ProgramizSwiftJiaochengChuyi/css/normalize.css
ProgramizSwiftJiaochengChuyi/css/popup.css
ProgramizSwiftJiaochengChuyi/font/__init__.py
ProgramizSwiftJiaochengChuyi/font/fontello.eot
ProgramizSwiftJiaochengChuyi/font/fontello.svg
ProgramizSwiftJiaochengChuyi/font/fontello.ttf
ProgramizSwiftJiaochengChuyi/font/fontello.woff
ProgramizSwiftJiaochengChuyi/img/__init__.py
ProgramizSwiftJiaochengChuyi/img/annotator-glyph-sprite.png
ProgramizSwiftJiaochengChuyi/img/annotator-icon-sprite.png
ProgramizSwiftJiaochengChuyi/img/apple-touch-icon.png
ProgramizSwiftJiaochengChuyi/img/cancelfullscreen.png
ProgramizSwiftJiaochengChuyi/img/close.png
ProgramizSwiftJiaochengChuyi/img/fullscreen.png
ProgramizSwiftJiaochengChuyi/img/loader.gif
ProgramizSwiftJiaochengChuyi/img/menu-icon.png
ProgramizSwiftJiaochengChuyi/img/save.png
ProgramizSwiftJiaochengChuyi/img/saved.png
ProgramizSwiftJiaochengChuyi/img/settings-s.png
ProgramizSwiftJiaochengChuyi/img/settings.png
ProgramizSwiftJiaochengChuyi/img/star.png
ProgramizSwiftJiaochengChuyi/js/__init__.py
ProgramizSwiftJiaochengChuyi/js/epub.js
ProgramizSwiftJiaochengChuyi/js/epub.min.js
ProgramizSwiftJiaochengChuyi/js/epub.min.map
ProgramizSwiftJiaochengChuyi/js/hooks.min.js
ProgramizSwiftJiaochengChuyi/js/hooks.min.map
ProgramizSwiftJiaochengChuyi/js/reader.js
ProgramizSwiftJiaochengChuyi/js/reader.js.map
ProgramizSwiftJiaochengChuyi/js/reader.min.js
ProgramizSwiftJiaochengChuyi/js/reader.min.map
ProgramizSwiftJiaochengChuyi/js/hooks/__init__.py
ProgramizSwiftJiaochengChuyi/js/hooks/extensions/__init__.py
ProgramizSwiftJiaochengChuyi/js/hooks/extensions/highlight.js
programiz_swift_jiaocheng_chuyi-2024.3.5.0.dist-info/METADATA
programiz_swift_jiaocheng_chuyi-2024.3.5.0.dist-info/WHEEL
programiz_swift_jiaocheng_chuyi-2024.3.5.0.dist-info/entry_points.txt
programiz_swift_jiaocheng_chuyi-2024.3.5.0.dist-info/top_level.txt
programiz_swift_jiaocheng_chuyi-2024.3.5.0.dist-info/RECORD
